Workbook

Sheet Assumptions
A1: Sovereign Mirror — Compute Cost Curves
A2: Analyst model: Local lab vs GPU rental (GSTD-class / cloud). Blue/yellow = inputs. All other values are formulas.
A4: 1. LOCAL LAB CAPEX SCENARIOS
A5: Scenario | B5: Capex ($) | C5: Annual power/ops ($) | D5: Useful life (yrs) | E5: Annualized capex ($/yr) | F5: Fully loaded yr cost ($)
A6: Lab_5k | B6: 5000 | C6: 250 | D6: 4 | E6: =B6/D6 | F6: =E6+C6
A7: Lab_15k | B7: 15000 | C7: 400 | D7: 4 | E7: =B7/D7 | F7: =E7+C7
A8: Lab_25k | B8: 25000 | C8: 550 | D8: 4 | E8: =B8/D8 | F8: =E8+C8
A10: 2. RENTAL COST PER TRAINING RUN ($/job)
A11: Job profile | B11: GSTD / decen. net ($) | C11: Commodity cloud ($) | D11: Blended rental ($) | E11: Notes
A12: QLoRA_7B_14B | B12: 15 | C12: 25 | D12: =ROUND((B12+C12)/2,0) | E12: Starter mirror iterate
A13: QLoRA_32B | B13: 60 | C13: 100 | D13: =ROUND((B13+C13)/2,0) | E13: Athena-class scale
A14: QLoRA_70B_or_long | B14: 150 | C14: 250 | D14: =ROUND((B14+C14)/2,0) | E14: Burst / research
A15: Infer_month_heavy | B15: 40 | C15: 60 | D15: =ROUND((B15+C15)/2,0) | E15: Always-on rented infer equiv
A17: 3. USAGE INTENSITY (runs / year of primary job)
A18: Intensity | B18: Runs/year | C18: Description
A19: Sparse | B19: 4 | C19: Quarterly retrain / experiments
A20: Moderate | B20: 24 | C20: Twice monthly iteration
A21: Heavy | B21: 52 | C21: Weekly train cycle
A22: Industrial | B22: 120 | C22: Near-continuous R&D
A24: 4. GLOBAL CONTROLS
A25: Primary job profile row (12=7B, 13=32B, 14=70B) | B25: 13
A26: Horizon years for TCO | B26: 5
A27: Discount rate (reference) | B27: 0.08
A28: Sovereignty premium ($/yr value of local control) | B28: 500
A29: Data-risk penalty for rental ($/yr) | B29: 300
A31: Sources / methodology
A32: Capex: project lab BOM tiers ($5k/$15k/$25k). Rental: illustrative mid-2026 GPU market ranges for QLoRA-class jobs (commodity cloud + decentralized nets). NOT an official GSTD tariff — replace yellow cells with live quotes. Power: ~$0.12–0.20/kWh duty cycle estimate. Sovereignty/risk adders are explicit judgment parameters for adjusted TCO.

Sheet Executive_Findings
A1: Executive findings — Compute cost-benefit (Sovereign Mirror)
A2: Decision support | Operator: build lab vs rent GSTD/cloud | Horizon: 5 years | Open model: recompute when yellow inputs change
A4: ID | B4: Finding | C4: Detail
A5: F1 | B5: Cash break-even is intensity-driven | C5: At default ~$80/job (32B blended), Lab_5k needs ~62 runs to recover capex. That is ~15.6 yrs at Sparse (4/yr), ~2.6 yrs Moderate (24/yr), ~1.2 yrs Heavy (52/yr), ~0.5 yrs Industrial (120/yr). Ownership is not always cheaper — it is cheaper when you iterate.
A6: F2 | B6: Sparse training favors rental / GSTD-class nets | C6: Few trains per year while learning scaffolds: pay-per-job dominates $5–25k capex. Capital stays liquid; silicon is not idle. GSTD competes with cloud on $/hr — not free.
A7: F3 | B7: Moderate-to-heavy iteration flips to OWN on cash alone | C7: Weekly / twice-monthly QLoRA (living sovereign mirror) tends to make Lab_5k cheaper over 5 years than renting equivalent jobs, before any sovereignty premium.
A8: F4 | B8: Lab_15k / Lab_25k need heavier use or non-cash value | C8: Larger labs clear pure cash break-even only at high run rates or expensive jobs (70B). Buy up for 32B+ headroom / multi-experiment — not status.
A9: F5 | B9: Adjusted TCO shifts frontier toward OWN | C9: Modest $/yr for (a) not uploading rope and (b) offline/no-token control moves several Moderate cases from RENT to OWN. Set shadow prices explicitly (Assumptions B28–B29).
A10: F6 | B10: GSTD is not free compute | C10: Decentralized nets still price GPU time. Prefer when cheaper AND capable of custom LoRA + private datasets. Pure consumption = cloud with a token skin; running a node is different.
A11: F7 | B11: Optimal policy is hybrid | C11: (1) $0 craft; (2) $50–300 proof job; (3) Lab_5k when intensity approaches Moderate; (4) rent 70B bursts; (5) delay Lab_15/25 until 32B is routine. Minimizes regret under uncertain train frequency.
A12: F8 | B12: Dominant sensitivity is $/job | C12: If rental falls to $15/job, even Heavy use delays $25k justification. If $150+/job, Lab_5k wins quickly. Re-quote yellow cells; all curves recompute.
A14: RECOMMENDATION MATRIX
A15: If expected runs/year… | B15: Primary | C15: Secondary
A16: ≤ 6 (Sparse) | B16: RENT / GSTD for trains | C16: No lab until intensity proven
A17: 12–30 (Moderate) | B17: Lab_5k within 12 months | C17: Rent for 70B bursts only
A18: 40–60 (Heavy) | B18: Lab_5k now; plan 2nd GPU | C18: GSTD only if cheaper than power+time
A19: 100+ (Industrial) | B19: Lab_15k–25k path | C19: Hybrid multi-node / supply-side GSTD
A21: DECISION RULE
A22: OWN if: (Runs/yr × $/run × Years) + Risk$/yr×Years > Capex + Ops×Years − Sov$/yr×Years
A23: Else RENT. Recompute when any yellow input changes. See BreakEven + TCO_Curves sheets.
A25: ILLUSTRATIVE POINT ESTIMATES (default assumptions, 32B job ~$80)
A26: Metric | B26: Value
A27: Lab_5k break-even runs @ $80/job | B27: 62.5
A28: 5yr Sparse rent (4×$80×5) | B28: $1,600
A29: 5yr Moderate rent (24×$80×5) | B29: $9,600
A30: 5yr Heavy rent (52×$80×5) | B30: $20,800
A31: 5yr Lab_5k cash (5k+5×250) | B31: $6,250
A32: Cash winner Sparse | B32: RENT (save ~$4.6k)
A33: Cash winner Moderate | B33: OWN (save ~$3.4k)
A34: Cash winner Heavy | B34: OWN (save ~$14.6k)

Sheet BreakEven
A1: Break-even analysis — rental vs local lab
A2: Break-even runs = Capex / ($/run). Below that run count, rent wins on cash; above, own wins.
A4: Primary job $/run (blended, from Assumptions) | B4: =INDEX(Assumptions!D12:D15,Assumptions!B25-11)
A6: Lab scenario | B6: Capex | C6: $/run | D6: Break-even runs | E6: Yrs @ Sparse(4) | F6: Yrs @ Moderate(24) | G6: Yrs @ Heavy(52) | H6: Yrs @ Industrial(120)
A7: =Assumptions!A6 | B7: =Assumptions!B6 | C7: =$B$4 | D7: =IF(C7=0,0,B7/C7) | E7: =D7/Assumptions!$B$19 | F7: =D7/Assumptions!$B$20 | G7: =D7/Assumptions!$B$21 | H7: =D7/Assumptions!$B$22
A8: =Assumptions!A7 | B8: =Assumptions!B7 | C8: =$B$4 | D8: =IF(C8=0,0,B8/C8) | E8: =D8/Assumptions!$B$19 | F8: =D8/Assumptions!$B$20 | G8: =D8/Assumptions!$B$21 | H8: =D8/Assumptions!$B$22
A9: =Assumptions!A8 | B9: =Assumptions!B8 | C9: =$B$4 | D9: =IF(C9=0,0,B9/C9) | E9: =D9/Assumptions!$B$19 | F9: =D9/Assumptions!$B$20 | G9: =D9/Assumptions!$B$21 | H9: =D9/Assumptions!$B$22
A11: Sensitivity: break-even runs vs $/run
A12: $/run | B12: BE Lab_5k | C12: BE Lab_15k | D12: BE Lab_25k
A13: 5 | B13: =Assumptions!$B$6/A13 | C13: =Assumptions!$B$7/A13 | D13: =Assumptions!$B$8/A13
A14: 10 | B14: =Assumptions!$B$6/A14 | C14: =Assumptions!$B$7/A14 | D14: =Assumptions!$B$8/A14
A15: 15 | B15: =Assumptions!$B$6/A15 | C15: =Assumptions!$B$7/A15 | D15: =Assumptions!$B$8/A15
A16: 20 | B16: =Assumptions!$B$6/A16 | C16: =Assumptions!$B$7/A16 | D16: =Assumptions!$B$8/A16
A17: 25 | B17: =Assumptions!$B$6/A17 | C17: =Assumptions!$B$7/A17 | D17: =Assumptions!$B$8/A17
A18: 30 | B18: =Assumptions!$B$6/A18 | C18: =Assumptions!$B$7/A18 | D18: =Assumptions!$B$8/A18
A19: 40 | B19: =Assumptions!$B$6/A19 | C19: =Assumptions!$B$7/A19 | D19: =Assumptions!$B$8/A19
A20: 50 | B20: =Assumptions!$B$6/A20 | C20: =Assumptions!$B$7/A20 | D20: =Assumptions!$B$8/A20
A21: 60 | B21: =Assumptions!$B$6/A21 | C21: =Assumptions!$B$7/A21 | D21: =Assumptions!$B$8/A21
A22: 75 | B22: =Assumptions!$B$6/A22 | C22: =Assumptions!$B$7/A22 | D22: =Assumptions!$B$8/A22
A23: 100 | B23: =Assumptions!$B$6/A23 | C23: =Assumptions!$B$7/A23 | D23: =Assumptions!$B$8/A23
A24: 125 | B24: =Assumptions!$B$6/A24 | C24: =Assumptions!$B$7/A24 | D24: =Assumptions!$B$8/A24
... A27: 200 | B27: =Assumptions!$B$6/A27 | C27: =Assumptions!$B$7/A27 | D27: =Assumptions!$B$8/A27

Sheet TCO_Curves
A1: 5-year cumulative cash TCO curves
A2: Year 0: lab = full capex, rent = $0. Later years: rent = cumulative jobs; lab = capex + cumulative ops.
A4: Job $/run | B4: =INDEX(Assumptions!D12:D15,Assumptions!B25-11)
A6: Year | B6: Rent Sparse | C6: Rent Moderate | D6: Rent Heavy | E6: Rent Industrial | F6: Own Lab_5k | G6: Own Lab_15k | H6: Own Lab_25k
A7: 0 | B7: 0 | C7: 0 | D7: 0 | E7: 0 | F7: =Assumptions!B6 | G7: =Assumptions!B7 | H7: =Assumptions!B8
A8: 1 | B8: =A8*Assumptions!$B$19*$B$4 | C8: =A8*Assumptions!$B$20*$B$4 | D8: =A8*Assumptions!$B$21*$B$4 | E8: =A8*Assumptions!$B$22*$B$4 | F8: =Assumptions!$B$6+A8*Assumptions!$C$6 | G8: =Assumptions!$B$7+A8*Assumptions!$C$7 | H8: =Assumptions!$B$8+A8*Assumptions!$C$8
A9: 2 | B9: =A9*Assumptions!$B$19*$B$4 | C9: =A9*Assumptions!$B$20*$B$4 | D9: =A9*Assumptions!$B$21*$B$4 | E9: =A9*Assumptions!$B$22*$B$4 | F9: =Assumptions!$B$6+A9*Assumptions!$C$6 | G9: =Assumptions!$B$7+A9*Assumptions!$C$7 | H9: =Assumptions!$B$8+A9*Assumptions!$C$8
A10: 3 | B10: =A10*Assumptions!$B$19*$B$4 | C10: =A10*Assumptions!$B$20*$B$4 | D10: =A10*Assumptions!$B$21*$B$4 | E10: =A10*Assumptions!$B$22*$B$4 | F10: =Assumptions!$B$6+A10*Assumptions!$C$6 | G10: =Assumptions!$B$7+A10*Assumptions!$C$7 | H10: =Assumptions!$B$8+A10*Assumptions!$C$8
A11: 4 | B11: =A11*Assumptions!$B$19*$B$4 | C11: =A11*Assumptions!$B$20*$B$4 | D11: =A11*Assumptions!$B$21*$B$4 | E11: =A11*Assumptions!$B$22*$B$4 | F11: =Assumptions!$B$6+A11*Assumptions!$C$6 | G11: =Assumptions!$B$7+A11*Assumptions!$C$7 | H11: =Assumptions!$B$8+A11*Assumptions!$C$8
A12: 5 | B12: =A12*Assumptions!$B$19*$B$4 | C12: =A12*Assumptions!$B$20*$B$4 | D12: =A12*Assumptions!$B$21*$B$4 | E12: =A12*Assumptions!$B$22*$B$4 | F12: =Assumptions!$B$6+A12*Assumptions!$C$6 | G12: =Assumptions!$B$7+A12*Assumptions!$C$7 | H12: =Assumptions!$B$8+A12*Assumptions!$C$8
A32: Year-5 cash comparison by intensity
A33: Intensity | B33: 5yr Rent | C33: 5yr Lab_5k | D33: 5yr Lab_15k | E33: Cash winner | F33: Rent - Lab5k
A34: Sparse | B34: =5*Assumptions!B19*$B$4 | C34: =Assumptions!B6+5*Assumptions!C6 | D34: =Assumptions!B7+5*Assumptions!C7 | E34: =IF(B34<=C34,"RENT","OWN Lab_5k") | F34: =B34-C34
A35: Moderate | B35: =5*Assumptions!B20*$B$4 | C35: =Assumptions!B6+5*Assumptions!C6 | D35: =Assumptions!B7+5*Assumptions!C7 | E35: =IF(B35<=C35,"RENT","OWN Lab_5k") | F35: =B35-C35
A36: Heavy | B36: =5*Assumptions!B21*$B$4 | C36: =Assumptions!B6+5*Assumptions!C6 | D36: =Assumptions!B7+5*Assumptions!C7 | E36: =IF(B36<=C36,"RENT","OWN Lab_5k") | F36: =B36-C36
A37: Industrial | B37: =5*Assumptions!B22*$B$4 | C37: =Assumptions!B6+5*Assumptions!C6 | D37: =Assumptions!B7+5*Assumptions!C7 | E37: =IF(B37<=C37,"RENT","OWN Lab_5k") | F37: =B37-C37
A39: Positive delta = rent costs MORE than Lab_5k over 5 years (ownership wins on cash).

Sheet Adjusted_TCO
A1: Adjusted TCO — cash + sovereignty − rental data risk
A2: Own gets annual sovereignty credit; rent gets annual data-risk charge. Both from Assumptions.
A4: Sovereignty benefit $/yr (own) | B4: =Assumptions!B28
A5: Data-risk cost $/yr (rent) | B5: =Assumptions!B29
A7: Intensity | B7: 5yr Rent cash | C7: 5yr Rent + risk | D7: 5yr Lab_5k cash | E7: 5yr Lab − sov credit | F7: Adj winner | G7: Adj rent − adj own
A8: Sparse | B8: =5*Assumptions!B19*INDEX(Assumptions!D12:D15,Assumptions!B25-11) | C8: =B8+5*$B$5 | D8: =Assumptions!B6+5*Assumptions!C6 | E8: =D8-5*$B$4 | F8: =IF(C8<=E8,"RENT","OWN") | G8: =C8-E8
A9: Moderate | B9: =5*Assumptions!B20*INDEX(Assumptions!D12:D15,Assumptions!B25-11) | C9: =B9+5*$B$5 | D9: =Assumptions!B6+5*Assumptions!C6 | E9: =D9-5*$B$4 | F9: =IF(C9<=E9,"RENT","OWN") | G9: =C9-E9
A10: Heavy | B10: =5*Assumptions!B21*INDEX(Assumptions!D12:D15,Assumptions!B25-11) | C10: =B10+5*$B$5 | D10: =Assumptions!B6+5*Assumptions!C6 | E10: =D10-5*$B$4 | F10: =IF(C10<=E10,"RENT","OWN") | G10: =C10-E10
A11: Industrial | B11: =5*Assumptions!B22*INDEX(Assumptions!D12:D15,Assumptions!B25-11) | C11: =B11+5*$B$5 | D11: =Assumptions!B6+5*Assumptions!C6 | E11: =D11-5*$B$4 | F11: =IF(C11<=E11,"RENT","OWN") | G11: =C11-E11
A13: Positive G = rent still more expensive after risk/sov → OWN preferred on adjusted basis.

Sheet Scenario_Grid
A1: Full scenario grid — 5yr cash TCO ($)
A3: Runs/yr | B3: 4 | C3: 12 | D3: 24 | E3: 36 | F3: 52 | G3: 80 | H3: 120
A4: Option | B4: 4/yr | C4: 12/yr | D4: 24/yr | E4: 36/yr | F4: 52/yr | G4: 80/yr | H4: 120/yr
A5: Rent 5yr | B5: =5*B3*INDEX(Assumptions!$D$12:$D$15,Assumptions!$B$25-11) | C5: =5*C3*INDEX(Assumptions!$D$12:$D$15,Assumptions!$B$25-11) | D5: =5*D3*INDEX(Assumptions!$D$12:$D$15,Assumptions!$B$25-11) | E5: =5*E3*INDEX(Assumptions!$D$12:$D$15,Assumptions!$B$25-11) | F5: =5*F3*INDEX(Assumptions!$D$12:$D$15,Assumptions!$B$25-11) | G5: =5*G3*INDEX(Assumptions!$D$12:$D$15,Assumptions!$B$25-11) | H5: =5*H3*INDEX(Assumptions!$D$12:$D$15,Assumptions!$B$25-11)
A6: Lab_5k 5yr | B6: =Assumptions!$B$6+5*Assumptions!$C$6 | C6: =Assumptions!$B$6+5*Assumptions!$C$6 | D6: =Assumptions!$B$6+5*Assumptions!$C$6 | E6: =Assumptions!$B$6+5*Assumptions!$C$6 | F6: =Assumptions!$B$6+5*Assumptions!$C$6 | G6: =Assumptions!$B$6+5*Assumptions!$C$6 | H6: =Assumptions!$B$6+5*Assumptions!$C$6
A7: Lab_15k 5yr | B7: =Assumptions!$B$7+5*Assumptions!$C$7 | C7: =Assumptions!$B$7+5*Assumptions!$C$7 | D7: =Assumptions!$B$7+5*Assumptions!$C$7 | E7: =Assumptions!$B$7+5*Assumptions!$C$7 | F7: =Assumptions!$B$7+5*Assumptions!$C$7 | G7: =Assumptions!$B$7+5*Assumptions!$C$7 | H7: =Assumptions!$B$7+5*Assumptions!$C$7
A8: Lab_25k 5yr | B8: =Assumptions!$B$8+5*Assumptions!$C$8 | C8: =Assumptions!$B$8+5*Assumptions!$C$8 | D8: =Assumptions!$B$8+5*Assumptions!$C$8 | E8: =Assumptions!$B$8+5*Assumptions!$C$8 | F8: =Assumptions!$B$8+5*Assumptions!$C$8 | G8: =Assumptions!$B$8+5*Assumptions!$C$8 | H8: =Assumptions!$B$8+5*Assumptions!$C$8
A9: Winner | B9: =IF(B5=MIN(B5:B8),"RENT",IF(B6=MIN(B5:B8),"L5k",IF(B7=MIN(B5:B8),"L15k","L25k"))) | C9: =IF(C5=MIN(C5:C8),"RENT",IF(C6=MIN(C5:C8),"L5k",IF(C7=MIN(C5:C8),"L15k","L25k"))) | D9: =IF(D5=MIN(D5:D8),"RENT",IF(D6=MIN(D5:D8),"L5k",IF(D7=MIN(D5:D8),"L15k","L25k"))) | E9: =IF(E5=MIN(E5:E8),"RENT",IF(E6=MIN(E5:E8),"L5k",IF(E7=MIN(E5:E8),"L15k","L25k"))) | F9: =IF(F5=MIN(F5:F8),"RENT",IF(F6=MIN(F5:F8),"L5k",IF(F7=MIN(F5:F8),"L15k","L25k"))) | G9: =IF(G5=MIN(G5:G8),"RENT",IF(G6=MIN(G5:G8),"L5k",IF(G7=MIN(G5:G8),"L15k","L25k"))) | H9: =IF(H5=MIN(H5:H8),"RENT",IF(H6=MIN(H5:H8),"L5k",IF(H7=MIN(H5:H8),"L15k","L25k")))
A11: Winner = pure cash minimum. L15k/L25k rarely win cash-only unless runs or $/job are high.
